MANIFEST.in
README.markdown
requirements.txt
setup.py
pin/__init__.py
pin/plugins/__init__.py
pin/plugins/pinpaver.py
pinpaver.egg-info/PKG-INFO
pinpaver.egg-info/SOURCES.txt
pinpaver.egg-info/dependency_links.txt
pinpaver.egg-info/namespace_packages.txt
pinpaver.egg-info/requires.txt
pinpaver.egg-info/top_level.txt