Metadata-Version: 1.1
Name: pinpaver
Version: 0.1rc1
Summary: Paver plugins for pin
Home-page: https://github.com/dustinlacewell/pin-fabric
Author: Dustin Lacewell
Author-email: dlacewell@gmail.com
License: UNKNOWN
Platform: UNKNOWN
Provides: pinpaver
